quickthumb/__init__.py
quickthumb/canvas.py
quickthumb/errors.py
quickthumb/font_cache.py
quickthumb/models.py
quickthumb-0.2.0.dist-info/METADATA
quickthumb-0.2.0.dist-info/WHEEL
quickthumb-0.2.0.dist-info/licenses/LICENSE
quickthumb-0.2.0.dist-info/RECORD
