Metadata-Version: 2.4
Name: quickthumb
Version: 0.2.0
Summary: A Python library for programmatic thumbnail generation
Author: Seonu Jang
License: MIT
License-File: LICENSE
Requires-Python: >=3.10
Requires-Dist: pillow<11.0.0,>=10.4.0
Requires-Dist: pydantic<3.0.0,>=2.12.5
Requires-Dist: typing-extensions<5.0.0,>=4.15.0
